wispy/__init__.py
wispy/classes.py
wispy/main.py
wisp.py-0.1.0.dist-info/LICENSE.md
wisp.py-0.1.0.dist-info/METADATA
wisp.py-0.1.0.dist-info/WHEEL
wisp.py-0.1.0.dist-info/top_level.txt
wisp.py-0.1.0.dist-info/RECORD
