Metadata-Version: 2.1
Name: wisp.py
Version: 0.1.0
Summary: A tiny Python package to interect with the WISP.gg API.
Home-page: https://github.com/MM-coder/wispy
Author: Mauro M.
Author-email: hello@maurom.dev
License: UNKNOWN
Keywords: wisp,api-wrapper,api,gaming,wrapper
Platform: UNKNOWN
Classifier: Programming Language :: Python :: 3
Classifier: Programming Language :: Python :: 3.5
Classifier: Programming Language :: Python :: 3.6
Classifier: Programming Language :: Python :: 3.7
Classifier: Programming Language :: Python :: 3.8
Classifier: Operating System :: OS Independent
Requires-Python: !=3.0.*, !=3.1.*, !=3.2.*, !=3.3.*, !=3.4.*
